spotify_cmd-0.1.16.dist-info/licenses/LICENSE.md
src/__init__.py
src/common/__init__.py
src/common/config.py
src/common/socket_data_handler.py
src/common/socket_message.py
src/spotify_cmd_client/__init__.py
src/spotify_cmd_client/client.py
src/spotify_cmd_client/data_presenter.py
src/spotify_cmd_client/main.py
src/spotify_cmd_daemon/__init__.py
src/spotify_cmd_daemon/main.py
src/spotify_cmd_daemon/socket_server.py
src/spotify_cmd_daemon/spotify_controller.py
src/spotify_cmd_daemon/operations/__init__.py
src/spotify_cmd_daemon/operations/get_library_albums.py
src/spotify_cmd_daemon/operations/get_library_playlists.py
src/spotify_cmd_daemon/operations/next_track.py
src/spotify_cmd_daemon/operations/pause_playback.py
src/spotify_cmd_daemon/operations/previous_track.py
src/spotify_cmd_daemon/operations/resume_playback.py
src/spotify_cmd_daemon/operations/search.py
src/spotify_cmd_daemon/operations/set_shuffle.py
src/spotify_cmd_daemon/operations/set_volume.py
src/spotify_cmd_daemon/operations/start_playback.py
src/spotify_cmd_daemon/operations/helpers/__init__.py
src/spotify_cmd_daemon/operations/helpers/check_resource_existence.py
src/spotify_cmd_daemon/operations/helpers/get_album.py
src/spotify_cmd_daemon/operations/helpers/get_playlist.py
src/spotify_cmd_daemon/operations/helpers/get_resource_from_library.py
src/spotify_cmd_daemon/operations/helpers/get_resource_uri.py
src/spotify_cmd_daemon/operations/presenters/__init__.py
src/spotify_cmd_daemon/operations/presenters/albums_presenter.py
src/spotify_cmd_daemon/operations/presenters/artists_presenter.py
src/spotify_cmd_daemon/operations/presenters/collection_presenter.py
src/spotify_cmd_daemon/operations/presenters/episodes_presenter.py
src/spotify_cmd_daemon/operations/presenters/playlists_presenter.py
src/spotify_cmd_daemon/operations/presenters/shows_presenter.py
src/spotify_cmd_daemon/operations/presenters/tracks_presenter.py
src/spotify_cmd_daemon/operations/validators/__init__.py
src/spotify_cmd_daemon/operations/validators/validate_resource_uri.py
spotify_cmd-0.1.16.dist-info/METADATA
spotify_cmd-0.1.16.dist-info/WHEEL
spotify_cmd-0.1.16.dist-info/entry_points.txt
spotify_cmd-0.1.16.dist-info/top_level.txt
spotify_cmd-0.1.16.dist-info/RECORD
