Metadata-Version: 2.4
Name: spotify-cmd
Version: 0.1.16
Summary: Command line Spotify client
Home-page: https://github.com/ciembor/spotify-cmd
Author: Maciej Ciemborowicz
Author-email: maciej.ciemborowicz@gmail.com
License: GNU General Public License v3.0
Classifier: Development Status :: 4 - Beta
Classifier: Intended Audience :: End Users/Desktop
Classifier: Topic :: Multimedia :: Sound/Audio :: Players
Classifier: License :: OSI Approved :: GNU General Public License v3 (GPLv3)
Classifier: Natural Language :: English
Classifier: Operating System :: POSIX :: Linux
Classifier: Operating System :: MacOS
Classifier: Programming Language :: Python :: 3
Classifier: Programming Language :: Python :: 3.6
Classifier: Programming Language :: Python :: 3.7
Classifier: Programming Language :: Python :: 3.8
Classifier: Programming Language :: Python :: 3.9
Classifier: Programming Language :: Python :: 3.10
Classifier: Programming Language :: Python :: 3.11
License-File: LICENSE.md
Requires-Dist: argparse==1.4.0
Requires-Dist: configparser==5.0.2
Requires-Dist: spotipy==2.23.0
Requires-Dist: python-daemon==3.0.1
Dynamic: author
Dynamic: author-email
Dynamic: classifier
Dynamic: description
Dynamic: description-content-type
Dynamic: home-page
Dynamic: license
Dynamic: license-file
Dynamic: requires-dist
Dynamic: summary
